pypotato
