Metadata-Version: 2.1
Name: pypotato
Version: 1.3.6
Summary: Python API to control programmable potentiostats.
Home-page: https://github.com/jrlLAB/pypotato
Author: Oliver Rodriguez
Author-email: oliver.rdz@softpotato.xyz
Keywords: Electrochemistry
License-File: LICENSE
